funmodel/__init__.py
funmodel/mivolo/__init__.py
funmodel/mivolo/predictor.py
funmodel/mivolo/structures.py
funmodel/mivolo/version.py
funmodel/mivolo/data/__init__.py
funmodel/mivolo/data/data_reader.py
funmodel/mivolo/data/misc.py
funmodel/mivolo/data/dataset/__init__.py
funmodel/mivolo/data/dataset/age_gender_dataset.py
funmodel/mivolo/data/dataset/age_gender_loader.py
funmodel/mivolo/data/dataset/classification_dataset.py
funmodel/mivolo/data/dataset/reader_age_gender.py
funmodel/mivolo/model/__init__.py
funmodel/mivolo/model/create_timm_model.py
funmodel/mivolo/model/cross_bottleneck_attn.py
funmodel/mivolo/model/mi_volo.py
funmodel/mivolo/model/mivolo_model.py
funmodel/mivolo/model/yolo_detector.py
funmodel_mivolo-0.0.9.dist-info/LICENSE
funmodel_mivolo-0.0.9.dist-info/METADATA
funmodel_mivolo-0.0.9.dist-info/WHEEL
funmodel_mivolo-0.0.9.dist-info/top_level.txt
funmodel_mivolo-0.0.9.dist-info/RECORD
